{
  "gestión de abastecimiento": "GESTIÓN DE ABASTECIMIENTO",
  "gestión y desarrollo del talento humano": "GESTIÓN Y DESARROLLO DEL TALENTO HUMANO",
  "gestión de la tecnología e innovación digital": "GESTIÓN DE LA TECNOLOGÍA E INNOVACIÓN DIGITAL",
  "auditoría interna": "AUDITORÍA INTERNA",
  "gestión de seguridad y salud en el trabajo": "GESTIÓN DE SEGURIDAD Y SALUD EN EL TRABAJO",
  "gestión infraestructura física": "INFRAESTRUCTURA Y SERVICIOS ADMINISTRATIVOS",
  "gestión de calidad": "PLANIFICACIÓN  Y MEJORA DEL SISTEMA INTEGRADO",
  "visibilidad nacional e internacional": "VISIBILIDAD NACIONAL E INTERNACIONAL",
  "biblioteca institucional": "RECURSOS ACADÉMICOS Y DE INVESTIGACIÓN",
  "investigación, desarrollo tecnológico, innovación y creación": "INVESTIGACIÓN, INNOVACIÓN Y CREACIÓN",
  "formación para la investigación, creación e innovación": "INVESTIGACIÓN, INNOVACIÓN Y CREACIÓN",
  "editorial y publicaciones": "RECURSOS ACADÉMICOS Y DE INVESTIGACIÓN",
  "servicio": "SERVICIO Y PERMANENCIA",
  "planeación financiera": "GESTIÓN FINANCIERA",
  "gestión ambiental": "GESTIÓN AMBIENTAL",
  "planificación polisigs": "PLANIFICACIÓN  Y MEJORA DEL SISTEMA INTEGRADO",
  "gestión de proyectos": "DIRECCIONAMIENTO ESTRATÉGICO",
  "permanencia": "SERVICIO Y PERMANENCIA",
  "registro y control": "SERVICIO Y PERMANENCIA",
  "gestión, evaluación e innovación curricular": "GESTIÓN DE PORTAFOLIO INSTITUCIONAL",
  "planeación estratégica": "DIRECCIONAMIENTO ESTRATÉGICO",
  "desempeño institucional": "DIRECCIONAMIENTO ESTRATÉGICO",
  "rematrícula": "SERVICIO Y PERMANENCIA",
  "gestión jurídica y normativa": "GESTIÓN JURÍDICA Y NORMATIVA",
  "centro de medios audiovisuales": "RECURSOS ACADÉMICOS Y DE INVESTIGACIÓN",
  "autoevaluación de programas académicos": "AUTOEVALUACIÓN Y AUTOREGULACIÓN",
  "experiencia institucional": "EXPERIENCIA INSTITUCIONAL",
  "gestión docente": "DOCENCIA",
  "cultura y deporte": "BIENESTAR INSTITUCIONAL",
  "gestión de riesgos": "GESTIÓN DE RIESGOS",
  "administración de servicios generales": "INFRAESTRUCTURA Y SERVICIOS ADMINISTRATIVOS",
  "servicio de salud": "BIENESTAR INSTITUCIONAL",
  "creación, modificación y cierre de programas académicos": "GESTIÓN DE PORTAFOLIO INSTITUCIONAL",
  "gestión de graduados": "EXTENSIÓN",
  "autoevaluación institucional": "AUTOEVALUACIÓN Y AUTOREGULACIÓN",
  "contabilidad": "GESTIÓN FINANCIERA",
  "datos y analítica": "DATOS Y ANALÍTICA",
  "tesorería": "GESTIÓN FINANCIERA",
  "prácticas": "EXTENSIÓN",
  "gestión de la responsabilidad social": "EXTENSIÓN",
  "operaciones académicas": "DOCENCIA",
  "operación de nuevos negocios y ci": "EXTENSIÓN",
  "inscripción, admisión y matrícula de estudiantes nuevos": "MERCADEO, ADMISIONES  Y MATRÍCULA",
  "gestión de campañas integradas de marketing": "COMUNICACIÓN Y POSICIONAMIENTO ESTRATÉGICO",
  "comunicaciones externas": "COMUNICACIÓN Y POSICIONAMIENTO ESTRATÉGICO",
  "emprendimiento": "EXTENSIÓN",
  "lei": "RECURSOS ACADÉMICOS Y DE INVESTIGACIÓN",
  "mercadeo de programas académicos": "MERCADEO, ADMISIONES  Y MATRÍCULA",
  "mercadeo y venta de educación para la vida": "MERCADEO, ADMISIONES  Y MATRÍCULA",
  "comunicaciones internas": "COMUNICACIÓN Y POSICIONAMIENTO ESTRATÉGICO",
  "gestión de unidades académicas": "DOCENCIA",
  "diseño de contenido virtual": "GESTIÓN DE PORTAFOLIO INSTITUCIONAL",
  "estudios internos": "DIRECCIONAMIENTO ESTRATÉGICO"
}